LICENSE
MANIFEST.in
README.md
setup.py
tap_looker/__init__.py
tap_looker/client.py
tap_looker/discover.py
tap_looker/generate_schemas.py
tap_looker/schema.py
tap_looker/streams.py
tap_looker/sync.py
tap_looker/transform.py
tap_looker.egg-info/PKG-INFO
tap_looker.egg-info/SOURCES.txt
tap_looker.egg-info/dependency_links.txt
tap_looker.egg-info/entry_points.txt
tap_looker.egg-info/requires.txt
tap_looker.egg-info/top_level.txt
tap_looker/schemas/color_collections.json
tap_looker/schemas/connections.json
tap_looker/schemas/content_favorites.json
tap_looker/schemas/content_metadata.json
tap_looker/schemas/content_metadata_access.json
tap_looker/schemas/content_views.json
tap_looker/schemas/dashboard_elements.json
tap_looker/schemas/dashboard_filters.json
tap_looker/schemas/dashboard_layouts.json
tap_looker/schemas/dashboards.json
tap_looker/schemas/datagroups.json
tap_looker/schemas/explores.json
tap_looker/schemas/folders.json
tap_looker/schemas/git_branches.json
tap_looker/schemas/groups.json
tap_looker/schemas/groups_in_group.json
tap_looker/schemas/integration_hubs.json
tap_looker/schemas/integrations.json
tap_looker/schemas/lookml_dashboards.json
tap_looker/schemas/lookml_models.json
tap_looker/schemas/looks.json
tap_looker/schemas/merge_queries.json
tap_looker/schemas/model_sets.json
tap_looker/schemas/models.json
tap_looker/schemas/permission_sets.json
tap_looker/schemas/permissions.json
tap_looker/schemas/project_files.json
tap_looker/schemas/projects.json
tap_looker/schemas/queries.json
tap_looker/schemas/query_history.json
tap_looker/schemas/role_groups.json
tap_looker/schemas/roles.json
tap_looker/schemas/scheduled_plans.json
tap_looker/schemas/themes.json
tap_looker/schemas/user_attribute_group_values.json
tap_looker/schemas/user_attribute_values.json
tap_looker/schemas/user_attributes.json
tap_looker/schemas/user_login_lockouts.json
tap_looker/schemas/user_sessions.json
tap_looker/schemas/users.json
tap_looker/schemas/versions.json
tap_looker/schemas/workspaces.json